[
    {
        "name": "",
        "adresse": "",
        "telephone": "",
        "remboursement": ""
    },
    {
        "name": "",
        "adresse": "",
        "telephone": "",
        "remboursement": ""
    },
    {
        "name": "",
        "adresse": "",
        "telephone": "",
        "remboursement": ""
    },
    {
        "name": "",
        "adresse": "",
        "telephone": "",
        "remboursement": ""
    },
    {
        "name": "",
        "adresse": "",
        "telephone": "",
        "remboursement": ""
    },
    {
        "name": "",
        "adresse": "",
        "telephone": "",
        "remboursement": ""
    },
    {
        "name": "",
        "adresse": "",
        "telephone": "",
        "remboursement": ""
    },
    {
        "name": "",
        "adresse": "",
        "telephone": "",
        "remboursement": ""
    },
    {
        "name": "",
        "adresse": "",
        "telephone": "",
        "remboursement": ""
    }
]